README.rst
setup.py
cssdiff/__init__.py
cssdiff.egg-info/PKG-INFO
cssdiff.egg-info/SOURCES.txt
cssdiff.egg-info/dependency_links.txt
cssdiff.egg-info/entry_points.txt
cssdiff.egg-info/not-zip-safe
cssdiff.egg-info/requires.txt
cssdiff.egg-info/top_level.txt