Metadata-Version: 1.1
Name: cssdiff
Version: 0.1
Summary: semantic css diff
Home-page: https://github.com/podhmo/cssdiff
Author: podhmo
Author-email: UNKNOWN
License: UNKNOWN
Keywords: css,cssdiff,diff,semantic diff,web
Platform: UNKNOWN
Classifier: Programming Language :: Python
Classifier: Programming Language :: Python :: Implementation :: CPython
